ai_scrapping_toolkit/__init__.py
ai_scrapping_toolkit/api/__init__.py
ai_scrapping_toolkit/api/main.py
ai_scrapping_toolkit/api/models/__init__.py
ai_scrapping_toolkit/api/models/requests.py
ai_scrapping_toolkit/api/models/responses.py
ai_scrapping_toolkit/api/routers/__init__.py
ai_scrapping_toolkit/api/routers/embedding.py
ai_scrapping_toolkit/api/routers/export.py
ai_scrapping_toolkit/api/routers/extraction.py
ai_scrapping_toolkit/api/routers/processing.py
ai_scrapping_toolkit/api/routers/scraping.py
ai_scrapping_toolkit/cli/__init__.py
ai_scrapping_toolkit/cli/extract_data.py
ai_scrapping_toolkit/cli/run_api.py
ai_scrapping_toolkit/cli/web_scraper.py
ai_scrapping_toolkit/src/__init__.py
ai_scrapping_toolkit/src/embeddings/__init__.py
ai_scrapping_toolkit/src/embeddings/vector_db.py
ai_scrapping_toolkit/src/llm/__init__.py
ai_scrapping_toolkit/src/llm/data_extractor.py
ai_scrapping_toolkit/src/llm/enhanced_data_extractor.py
ai_scrapping_toolkit/src/llm/extraction.py
ai_scrapping_toolkit/src/llm/providers/__init__.py
ai_scrapping_toolkit/src/llm/providers/lmstudio_provider.py
ai_scrapping_toolkit/src/llm/providers/ollama_provider.py
ai_scrapping_toolkit/src/llm/providers/openai_provider.py
ai_scrapping_toolkit/src/llm/providers/openrouter_provider.py
ai_scrapping_toolkit/src/nlp/__init__.py
ai_scrapping_toolkit/src/nlp/query_analyzer.py
ai_scrapping_toolkit/src/processors/__init__.py
ai_scrapping_toolkit/src/processors/content_extractor.py
ai_scrapping_toolkit/src/processors/data_processor.py
ai_scrapping_toolkit/src/processors/html_chunker.py
ai_scrapping_toolkit/src/processors/html_preprocessor.py
ai_scrapping_toolkit/src/processors/pdf_processor.py
ai_scrapping_toolkit/src/processors/semantic_chunker.py
ai_scrapping_toolkit/src/scrapers/__init__.py
ai_scrapping_toolkit/src/scrapers/robots_checker.py
ai_scrapping_toolkit/src/scrapers/scraper.py
ai_scrapping_toolkit/src/scrapers/web_scraper.py
ai_scrapping_toolkit/src/utils/__init__.py
ai_scrapping_toolkit-1.0.1.dist-info/licenses/LICENSE
ai_scrapping_toolkit-1.0.1.dist-info/METADATA
ai_scrapping_toolkit-1.0.1.dist-info/WHEEL
ai_scrapping_toolkit-1.0.1.dist-info/entry_points.txt
ai_scrapping_toolkit-1.0.1.dist-info/top_level.txt
ai_scrapping_toolkit-1.0.1.dist-info/RECORD
