Metadata-Version: 2.4
Name: ai_scrapping_toolkit
Version: 1.0.1
Summary: Toolkit pour extraire, prétraiter et traiter des contenus web avec des modèles d'IA
Home-page: https://github.com/VynoDePal/AI-Scrapping
Author: Kevyn Odjo
Author-email: kevyn.odjo@example.com
License: MIT
Project-URL: Bug Tracker, https://github.com/VynoDePal/AI-Scrapping/issues
Project-URL: Documentation, https://github.com/VynoDePal/AI-Scrapping
Project-URL: Source Code, https://github.com/VynoDePal/AI-Scrapping
Classifier: Development Status :: 4 - Beta
Classifier: Intended Audience :: Developers
Classifier: Intended Audience :: Science/Research
Classifier: License :: OSI Approved :: MIT License
Classifier: Programming Language :: Python :: 3
Classifier: Programming Language :: Python :: 3.8
Classifier: Programming Language :: Python :: 3.9
Classifier: Programming Language :: Python :: 3.10
Classifier: Programming Language :: Python :: 3.11
Classifier: Topic :: Internet :: WWW/HTTP
Classifier: Topic :: Scientific/Engineering :: Artificial Intelligence
Classifier: Topic :: Software Development :: Libraries :: Python Modules
Classifier: Topic :: Text Processing :: Markup :: HTML
Requires-Python: >=3.8
License-File: LICENSE
Requires-Dist: requests>=2.28.0
Requires-Dist: beautifulsoup4>=4.11.0
Requires-Dist: nltk>=3.7
Requires-Dist: scikit-learn>=1.1.0
Requires-Dist: pandas>=1.4.0
Requires-Dist: numpy>=1.22.0
Requires-Dist: lxml>=4.9.0
Requires-Dist: selenium>=4.2.0
Requires-Dist: transformers>=4.20.0
Requires-Dist: sentence-transformers>=2.2.2
Requires-Dist: faiss-cpu>=1.7.3
Requires-Dist: webdriver-manager>=3.8.0
Requires-Dist: tqdm>=4.64.0
Requires-Dist: python-dotenv>=0.21.0
Requires-Dist: pymupdf>=1.21.1
Requires-Dist: PyPDF2>=2.12.1
Requires-Dist: pdf2image>=1.16.3
Requires-Dist: fastapi>=0.95.0
Requires-Dist: uvicorn>=0.21.0
Requires-Dist: python-multipart>=0.0.6
Requires-Dist: httpx>=0.24.0
Requires-Dist: aiofiles>=23.1.0
Requires-Dist: python-dateutil>=2.8.2
Requires-Dist: nltk>=3.7
Requires-Dist: openpyxl>=3.1.0
Requires-Dist: tabulate>=0.9.0
Requires-Dist: chardet>=5.1.0
Requires-Dist: colorama>=0.4.6
Requires-Dist: coverage>=7.3.0
Requires-Dist: pytest>=7.4.0
Requires-Dist: pytest-cov>=4.1.0
Dynamic: author
Dynamic: author-email
Dynamic: classifier
Dynamic: description
Dynamic: description-content-type
Dynamic: home-page
Dynamic: license
Dynamic: license-file
Dynamic: project-url
Dynamic: requires-dist
Dynamic: requires-python
Dynamic: summary
